steamlib/__init__.py
steamlib/schemas.py
steamlib/api/__init__.py
steamlib/api/enums.py
steamlib/api/facade.py
steamlib/api/account/__init__.py
steamlib/api/account/api.py
steamlib/api/account/enums.py
steamlib/api/account/exceptions.py
steamlib/api/account/schemas.py
steamlib/api/inventory/__init__.py
steamlib/api/inventory/api.py
steamlib/api/inventory/exceptions.py
steamlib/api/market/__init__.py
steamlib/api/market/api.py
steamlib/api/market/schemas.py
steamlib/api/store/__init__.py
steamlib/api/store/api.py
steamlib/api/store/purchase/__init__.py
steamlib/api/store/purchase/api.py
steamlib/api/store/purchase/schemas.py
steamlib/api/trade/__init__.py
steamlib/api/trade/api.py
steamlib/api/trade/exceptions.py
steamlib/api/trade/schemas.py
pysteamlib-1.0.1.dist-info/LICENSE
pysteamlib-1.0.1.dist-info/METADATA
pysteamlib-1.0.1.dist-info/WHEEL
pysteamlib-1.0.1.dist-info/top_level.txt
pysteamlib-1.0.1.dist-info/RECORD
