Metadata-Version: 2.1
Name: pysteamlib
Version: 1.0.1
Summary: Python Steam library
Home-page: https://github.com/sometastycake/pysteamlib
Author: Mike M
License: MIT
Requires-Python: >=3.9
License-File: LICENSE
Requires-Dist: pysteamauth ==1.1.2
Requires-Dist: aiofiles ==22.1.0
Requires-Dist: cssselect ==1.1.0
Requires-Dist: lxml ==5.3.0
